setup.py
zmt_geometric/__init__.py
zmt_geometric/const.py
zmt_geometric/main.py
zmt_geometric.egg-info/PKG-INFO
zmt_geometric.egg-info/SOURCES.txt
zmt_geometric.egg-info/dependency_links.txt
zmt_geometric.egg-info/not-zip-safe
zmt_geometric.egg-info/requires.txt
zmt_geometric.egg-info/top_level.txt