Metadata-Version: 2.1
Name: zmt-geometric
Version: 1.0.1
Summary: Geometric series interfaces.
Author: Michael Zhang
Author-email: zmtgoodboy2@gmail.com
License: MIT
Platform: any
